setup.py
mc_pi.egg-info/PKG-INFO
mc_pi.egg-info/SOURCES.txt
mc_pi.egg-info/dependency_links.txt
mc_pi.egg-info/top_level.txt
mcpi/__init__.py
mcpi/block.py
mcpi/connection.py
mcpi/event.py
mcpi/minecraft.py
mcpi/minecraftstuff.py
mcpi/util.py
mcpi/vec3.py