Metadata-Version: 1.0
Name: mc-pi
Version: 1.0.1.6
Summary: Refer to http://www.stuffaboutcode.com
Home-page: https://github.com/MrMenezes/mcpi
Author: Martin O'Hanlon
Author-email: sr.tama@outlook.com
License: UNKNOWN
Keywords: raspberry pi minecraft python tutorial
Platform: UNKNOWN
